CHANGES.txt
COPYRIGHT.txt
LICENSE.txt
MANIFEST.in
README.txt
setup.py
src/falkolab/__init__.py
src/falkolab.cacheburster.egg-info/PKG-INFO
src/falkolab.cacheburster.egg-info/SOURCES.txt
src/falkolab.cacheburster.egg-info/dependency_links.txt
src/falkolab.cacheburster.egg-info/namespace_packages.txt
src/falkolab.cacheburster.egg-info/not-zip-safe
src/falkolab.cacheburster.egg-info/requires.txt
src/falkolab.cacheburster.egg-info/top_level.txt
src/falkolab/cacheburster/README.txt
src/falkolab/cacheburster/__init__.py
src/falkolab/cacheburster/configure.zcml
src/falkolab/cacheburster/ftesting-base.zcml
src/falkolab/cacheburster/ftesting.zcml
src/falkolab/cacheburster/interfaces.py
src/falkolab/cacheburster/meta.zcml
src/falkolab/cacheburster/metaconfigure.py
src/falkolab/cacheburster/metadirectives.py
src/falkolab/cacheburster/rule.py
src/falkolab/cacheburster/testing.py
src/falkolab/cacheburster/url.py
src/falkolab/cacheburster/version.py
src/falkolab/cacheburster/view.py
src/falkolab/cacheburster/tests/__init__.py
src/falkolab/cacheburster/tests/test_directive.py
src/falkolab/cacheburster/tests/test_doc.py
src/falkolab/cacheburster/tests/testfiles/any_script.pack
src/falkolab/cacheburster/tests/testfiles/one-module.css
src/falkolab/cacheburster/tests/testfiles/page.pt
src/falkolab/cacheburster/tests/testfiles/page2.pt
src/falkolab/cacheburster/tests/testfiles/page3.pt
src/falkolab/cacheburster/tests/testfiles/script.js