Metadata-Version: 1.0
Name: falkolab.cacheburster
Version: 0.1.4
Summary: Manipulations with browser resource URL to forcing a browser to update its cache
Home-page: http://blog.falkolab.ru
Author: Andrey Tkachenko
Author-email: falko.lab@gmail.com
License: ZPL 2.1
Keywords: resource cache burster hash crc32 version
Platform: UNKNOWN
Classifier: Development Status :: 4 - Beta
Classifier: Environment :: Web Environment
Classifier: Framework :: Zope3
Classifier: Intended Audience :: Developers
Classifier: License :: OSI Approved :: Zope Public License
Classifier: Operating System :: OS Independent
Classifier: Programming Language :: Python
Classifier: Topic :: Internet :: WWW/HTTP
